LICENSE
MANIFEST.in
README.rst
nude.py
setup.py
skin_classifier.c
nudepy.egg-info/PKG-INFO
nudepy.egg-info/SOURCES.txt
nudepy.egg-info/dependency_links.txt
nudepy.egg-info/entry_points.txt
nudepy.egg-info/not-zip-safe
nudepy.egg-info/requires.txt
nudepy.egg-info/top_level.txt