Metadata-Version: 1.1
Name: nudepy
Version: 0.5.1
Summary: Nudity detection with Python. Port of nude.js to Python.
Home-page: https://github.com/hhatto/nude.py
Author: Hideo Hattori
Author-email: hhatto.jp@gmail.com
License: MIT
Keywords: nude
Platform: Linux
Classifier: Development Status :: 4 - Beta
Classifier: License :: OSI Approved :: MIT License
Classifier: Operating System :: POSIX :: Linux
Classifier: Programming Language :: Python
Classifier: Programming Language :: Python :: 2
Classifier: Programming Language :: Python :: 3
